{
  "id": "still-fighting-the-system",
  "title": "Still Fighting the System",
  "status": "published",
  "authors": [
    "alex"
  ],
  "excerpt": "Well, talking with the Director of Admissions at the University of North Dakota did nothing to help solve my Oldenburg transcript problem. She repeated exactly the same thing her subordinates did, offering no help whatsoever. I am becoming extremely frustrated at this point because they are unwilling (more likely unable) to comprehend the idea that &#8230; more &#x2192;\n",
  "categories": [
    "general"
  ],
  "tags": [
    "University of North Dakota"
  ],
  "publishedDate": "2009-03-10T20:30:30",
  "updatedAt": "2009-03-10T20:30:30",
  "wordpressId": 10687
}