{
  "id": "kids-room-now-available",
  "title": "Kid’s Room Now Available",
  "status": "published",
  "authors": [
    "alex"
  ],
  "excerpt": "My album, Kid&#8217;s Room, is now making its rounds to the different online stores. So far, it&#8217;s now available at the following stores, among others: Amazon.comNapster There are of course several other stores that it will be available at soon! Keep your eyes out for Kid&#8217;s Room arriving at your favorite store!\n",
  "categories": [
    "news",
    "stories",
    "music"
  ],
  "tags": [],
  "publishedDate": "2007-11-02T22:59:15",
  "updatedAt": "2025-09-14T22:51:00",
  "wordpressId": 1462
}