{
  "id": "england-photos",
  "title": "England Photos",
  "status": "published",
  "authors": [
    "alex"
  ],
  "excerpt": "I&#8217;m back from England now! I&#8217;ve posted photos from it here. I will write more about it later though. Also, there&#8217;s actually finally snow on the ground here. It&#8217;s the first time I&#8217;ve ever seen snow on the ground here.\n",
  "categories": [
    "trip-to-germany"
  ],
  "tags": [
    "New Photos"
  ],
  "publishedDate": "2008-03-25T12:37:15",
  "updatedAt": "2025-09-14T14:21:25",
  "wordpressId": 10165
}