{
  "id": "music-updates",
  "title": "Music Updates",
  "status": "published",
  "authors": [
    "alex"
  ],
  "excerpt": "My new album, The Living Room, was released on May 4, 2008! It will be available in stores soon, but until then, you can listen to the whole album on Last.fm. You can also now find me on Facebook! If you have a Facebook account, visit the page below and click the &#8220;Become a Fan&#8221; &#8230; more &#x2192;\n",
  "categories": [
    "stories",
    "music"
  ],
  "tags": [
    "Alex Seifert",
    "Dance",
    "Electronic"
  ],
  "publishedDate": "2008-05-06T00:14:41",
  "updatedAt": "2025-09-21T18:29:10",
  "wordpressId": 10423
}