{
  "id": "tales-of-fate-1",
  "title": "Tales of Fate 1",
  "status": "published",
  "authors": [
    "alex"
  ],
  "excerpt": "There I sat. In the darkness. Alone. My child had just died and I sat near his grave. I lifted my head and looked at the stars. There was a light breeze which I could feel in my hair. The sky was clear and all of the stars were bright and wonderful. They were so &#8230; more &#x2192;\n",
  "categories": [
    "projects",
    "writing"
  ],
  "tags": [
    "Tales of Fate"
  ],
  "publishedDate": "2009-06-03T12:31:34",
  "updatedAt": "2025-09-14T15:31:57",
  "wordpressId": 10497
}